rfconv/__init__.py
rfconv/function.py
rfconv/nn.py
rfconv/version.py
rfconv/lib/__init__.py
rfconv/lib/operator_cpu.cpp
rfconv/lib/operator_cuda.cpp
rfconv/lib/rectify_cpu.cpp
rfconv/lib/rectify_cuda.cu
rfconv/lib/utils.h
rfconv/models/__init__.py
rfconv/models/baseline.py
rfconv/models/resnet_variants.py
rfconv-0.0.2b20210406.dist-info/LICENSE
rfconv-0.0.2b20210406.dist-info/METADATA
rfconv-0.0.2b20210406.dist-info/WHEEL
rfconv-0.0.2b20210406.dist-info/top_level.txt
rfconv-0.0.2b20210406.dist-info/RECORD
